kafffffff00/__init__.py
kafffffff00/chat.py
kafffffff00-0.7.dist-info/METADATA
kafffffff00-0.7.dist-info/WHEEL
kafffffff00-0.7.dist-info/top_level.txt
kafffffff00-0.7.dist-info/RECORD
