Metadata-Version: 2.4
Name: kafffffff00
Version: 0.7
Summary: 1
Home-page: 
Author: pang7
Author-email: pang7ming@gmail.com
License: MIT
Requires-Dist: requests
Dynamic: author
Dynamic: author-email
Dynamic: license
Dynamic: requires-dist
Dynamic: summary
